pytest_circleci/__init__.py
pytest_circleci/plugin.py
patreon_pytest_circleci-0.1.0.dist-info/LICENSE
patreon_pytest_circleci-0.1.0.dist-info/METADATA
patreon_pytest_circleci-0.1.0.dist-info/WHEEL
patreon_pytest_circleci-0.1.0.dist-info/entry_points.txt
patreon_pytest_circleci-0.1.0.dist-info/top_level.txt
patreon_pytest_circleci-0.1.0.dist-info/RECORD
