Metadata-Version: 2.1
Name: patreon-pytest-circleci
Version: 0.1.0
Summary: py.test plugin for CircleCI
Home-page: https://github.com/Patreon/pytest-circlci
Author: Michael Twomey
Author-email: mick@twomeylee.name
License: UNKNOWN
Platform: UNKNOWN
Classifier: License :: OSI Approved :: MIT License
Classifier: Programming Language :: Python :: 2
Classifier: Programming Language :: Python :: 3
Requires-Dist: pytest
